{
  "number": "199",
  "direction": [
    [
      {
        "name": "Boon Lay Int",
        "code": "22009",
        "latlng": "103.705457018433,1.33932334709133"
      },
      {
        "name": "Blk 683A",
        "code": "22489",
        "latlng": "103.705368337922,1.34258460260953"
      },
      {
        "name": "Blk 680C",
        "code": "21371",
        "latlng": "103.706149030132,1.34523359172493"
      },
      {
        "name": "Opp Blk 271 CP",
        "code": "27091",
        "latlng": "103.703885000005,1.34910999997993"
      },
      {
        "name": "Westville",
        "code": "27101",
        "latlng": "103.70111638903,1.35259472200332"
      },
      {
        "name": "Bef Nanyang Ave",
        "code": "27121",
        "latlng": "103.695212777987,1.35682305601005"
      },
      {
        "name": "Bef Lor Danau",
        "code": "27171",
        "latlng": "103.691682544832,1.3560456505913"
      },
      {
        "name": "PUB Sub-Stn",
        "code": "27181",
        "latlng": "103.689036206381,1.35587588807389"
      },
      {
        "name": "Blk 55",
        "code": "27011",
        "latlng": "103.686109388702,1.35586334559421"
      },
      {
        "name": "Hall 15",
        "code": "27021",
        "latlng": "103.681929166994,1.35324138896647"
      },
      {
        "name": "Hall 12",
        "code": "27031",
        "latlng": "103.680517498399,1.35186815681842"
      },
      {
        "name": "CP Y",
        "code": "27041",
        "latlng": "103.678642471392,1.35071936245656"
      },
      {
        "name": "NIE Lib",
        "code": "27051",
        "latlng": "103.676658056004,1.34845333297034"
      },
      {
        "name": "Blk 2",
        "code": "27219",
        "latlng": "103.680252400169,1.34793269501079"
      },
      {
        "name": "Blk 41",
        "code": "27069",
        "latlng": "103.684184444028,1.35008972199844"
      },
      {
        "name": "Hall 8",
        "code": "27209",
        "latlng": "103.685692343311,1.35150701703319"
      },
      {
        "name": "Hall 11",
        "code": "27199",
        "latlng": "103.686857549383,1.35434216792732"
      },
      {
        "name": "Opp PUB Sub-Stn",
        "code": "27189",
        "latlng": "103.689039216903,1.35607204234298"
      },
      {
        "name": "Aft Lor Danau",
        "code": "27179",
        "latlng": "103.691782577312,1.35618418171949"
      },
      {
        "name": "Bef Jln Bahar",
        "code": "27169",
        "latlng": "103.694244642542,1.35693103245138"
      },
      {
        "name": "Opp Westville",
        "code": "27109",
        "latlng": "103.700823056019,1.3530947219982"
      },
      {
        "name": "Blk 271 CP",
        "code": "27099",
        "latlng": "103.703609998214,1.35023689448437"
      },
      {
        "name": "Blk 263",
        "code": "21379",
        "latlng": "103.706489129889,1.34534855216046"
      },
      {
        "name": "Blk 691A CP",
        "code": "22481",
        "latlng": "103.70554089547,1.34246223847423"
      },
      {
        "name": "Boon Lay Int",
        "code": "22009",
        "latlng": "103.705457018433,1.33932334709133"
      }
    ]
  ]
}
