{
  "number": "27",
  "direction": [
    [
      {
        "name": "Hougang Ctrl Int",
        "code": "64009",
        "latlng": "103.892668088747,1.37060695394607"
      },
      {
        "name": "Blk 522",
        "code": "64389",
        "latlng": "103.891568183885,1.37313809346002"
      },
      {
        "name": "Punggol CC",
        "code": "64379",
        "latlng": "103.892663061295,1.37468500843169"
      },
      {
        "name": "Bet Blks 544/546",
        "code": "64579",
        "latlng": "103.892680603091,1.37820828048179"
      },
      {
        "name": "Buangkok Stn",
        "code": "67609",
        "latlng": "103.893039785301,1.38393305306479"
      },
      {
        "name": "Blk 203B",
        "code": "67261",
        "latlng": "103.894642068665,1.38658741330895"
      },
      {
        "name": "Blk 203",
        "code": "67209",
        "latlng": "103.896181018133,1.38690839585983"
      },
      {
        "name": "Opp Blk 223D",
        "code": "67199",
        "latlng": "103.896891651336,1.38894870816309"
      },
      {
        "name": "Opp Blk 241",
        "code": "67189",
        "latlng": "103.89742612836,1.39059955869543"
      },
      {
        "name": "Blk 259C",
        "code": "67249",
        "latlng": "103.898504234664,1.39376571527273"
      },
      {
        "name": "Blk 297A",
        "code": "67259",
        "latlng": "103.900462389006,1.39465386086748"
      },
      {
        "name": "Blk 298A",
        "code": "65061",
        "latlng": "103.901859475913,1.39490129021004"
      },
      {
        "name": "Aft TPE",
        "code": "75359",
        "latlng": "103.93147946559,1.37438650022453"
      },
      {
        "name": "Opp HNS Micro Siltronic",
        "code": "75369",
        "latlng": "103.930565286043,1.37079630405205"
      },
      {
        "name": "Opp Tampines Dormitory",
        "code": "75319",
        "latlng": "103.9310545998,1.3672111961877"
      },
      {
        "name": "Bef Tampines Ave 9",
        "code": "75299",
        "latlng": "103.931066170328,1.36239101738977"
      },
      {
        "name": "Opp Blks 741/742",
        "code": "75289",
        "latlng": "103.933315557001,1.36048165638484"
      },
      {
        "name": "Opp Blk 721",
        "code": "75279",
        "latlng": "103.936203884456,1.36048469581497"
      },
      {
        "name": "Opp Tampines Reg Lib",
        "code": "76191",
        "latlng": "103.94476175309,1.3568670677916"
      },
      {
        "name": "Opp Tampines Stn/Int",
        "code": "76149",
        "latlng": "103.946367105605,1.3537072852719"
      },
      {
        "name": "Opp Century Sq",
        "code": "76139",
        "latlng": "103.943857462276,1.35162098693273"
      },
      {
        "name": "Blk 147",
        "code": "76069",
        "latlng": "103.942086290874,1.34875342113965"
      },
      {
        "name": "Airport Police Stn",
        "code": "95151",
        "latlng": "103.981817955411,1.34209640049894"
      },
      {
        "name": "Bef Changi Airport PTB3",
        "code": "95011",
        "latlng": "103.984060555585,1.34719486317061"
      },
      {
        "name": "Changi Airport PTB3",
        "code": "95109",
        "latlng": "103.98745068817,1.35599793849825"
      },
      {
        "name": "Changi Airport PTB1",
        "code": "95029",
        "latlng": "103.990699846841,1.36126748727777"
      },
      {
        "name": "Changi Airport PTB2",
        "code": "95129",
        "latlng": "103.989219540739,1.35509298857095"
      }
    ],
    [
      {
        "name": "Changi Airport PTB2",
        "code": "95129",
        "latlng": "103.989219540739,1.35509298857095"
      },
      {
        "name": "CIAS",
        "code": "95019",
        "latlng": "103.984345754315,1.34687172456468"
      },
      {
        "name": "Near SATS Flight Kitchen",
        "code": "95159",
        "latlng": "103.982388875963,1.34203653965317"
      },
      {
        "name": "Blk 938",
        "code": "76061",
        "latlng": "103.941874777289,1.34821131089716"
      },
      {
        "name": "UOB Tampines Ctr",
        "code": "76131",
        "latlng": "103.942541194165,1.35185810935571"
      },
      {
        "name": "Tampines Stn/Int",
        "code": "76141",
        "latlng": "103.946090604516,1.35366689108993"
      },
      {
        "name": "Bef Tampines Reg Lib",
        "code": "76199",
        "latlng": "103.945354284321,1.35660016333741"
      },
      {
        "name": "Blk 721",
        "code": "75271",
        "latlng": "103.936014950431,1.36024833439931"
      },
      {
        "name": "Blk 742A",
        "code": "75281",
        "latlng": "103.933638090951,1.36022789260444"
      },
      {
        "name": "Aft Tampines Ave 9",
        "code": "75291",
        "latlng": "103.930767207253,1.36149182194876"
      },
      {
        "name": "Tampines Dormitory",
        "code": "75311",
        "latlng": "103.930782079718,1.36707803417344"
      },
      {
        "name": "Bef Tampines Ind Ave 5",
        "code": "75361",
        "latlng": "103.930302344304,1.37064415458273"
      },
      {
        "name": "Bef TPE",
        "code": "75351",
        "latlng": "103.93077504302,1.37364163782278"
      },
      {
        "name": "Blk 190C",
        "code": "65069",
        "latlng": "103.902368248585,1.39504382175992"
      },
      {
        "name": "Blk 253",
        "code": "67251",
        "latlng": "103.900312185263,1.3944286220535"
      },
      {
        "name": "Blk 248A",
        "code": "67241",
        "latlng": "103.898468736862,1.39296197800719"
      },
      {
        "name": "Blk 240",
        "code": "67181",
        "latlng": "103.897780179965,1.39101786005689"
      },
      {
        "name": "Blk 223D",
        "code": "67191",
        "latlng": "103.897114523551,1.38908295100002"
      },
      {
        "name": "Blk 206A",
        "code": "67201",
        "latlng": "103.896288922469,1.38669709800437"
      },
      {
        "name": "Opp Blk 203A",
        "code": "67269",
        "latlng": "103.895133642315,1.38605407647497"
      },
      {
        "name": "Buangkok Stn",
        "code": "67601",
        "latlng": "103.893268327308,1.38334470717292"
      },
      {
        "name": "Blk 438",
        "code": "64571",
        "latlng": "103.892964942377,1.37811157042735"
      },
      {
        "name": "Opp Punggol CC",
        "code": "64371",
        "latlng": "103.892894273561,1.37447444021163"
      },
      {
        "name": "Opp Blk 521",
        "code": "64381",
        "latlng": "103.891707656754,1.37287245758112"
      },
      {
        "name": "Hougang Ctrl Int",
        "code": "64009",
        "latlng": "103.892668088747,1.37060695394607"
      }
    ]
  ]
}
