{
  "number": "410",
  "direction": [
    [
      {
        "name": "Bishan Int",
        "code": "53009",
        "latlng": "103.849880837223,1.35045541249508"
      },
      {
        "name": "Bishan Int",
        "code": "53009",
        "latlng": "103.849880837223,1.35045541249508"
      },
      {
        "name": "Opp Blk 203",
        "code": "53391",
        "latlng": "103.846963203253,1.35444291744508"
      },
      {
        "name": "Zion Bible Presby Ch",
        "code": "53289",
        "latlng": "103.854606422838,1.34723319800387"
      },
      {
        "name": "Blk 257",
        "code": "53371",
        "latlng": "103.843795683104,1.35994333341022"
      },
      {
        "name": "Blk 115",
        "code": "53221",
        "latlng": "103.84845435621,1.34816840593857"
      },
      {
        "name": "Bef Bright Hill Tp",
        "code": "53331",
        "latlng": "103.837012778021,1.36285472197705"
      },
      {
        "name": "Opp Sunrise Co Pte Ltd",
        "code": "53311",
        "latlng": "103.841623888996,1.34684500003065"
      },
      {
        "name": "Ai Tong Sch",
        "code": "53351",
        "latlng": "103.832117500013,1.36080972198453"
      },
      {
        "name": "Shunfu Mart",
        "code": "53291",
        "latlng": "103.837113976486,1.35231394964538"
      },
      {
        "name": "Opp Windsor Pk",
        "code": "53069",
        "latlng": "103.828943510471,1.35777159286248"
      },
      {
        "name": "Bef Thomson Ridge",
        "code": "53041",
        "latlng": "103.834363959767,1.3530783161276"
      },
      {
        "name": "Aft Thomson Rd PO",
        "code": "53049",
        "latlng": "103.834221723615,1.35362664583061"
      },
      {
        "name": "Thomson View Condo",
        "code": "53061",
        "latlng": "103.828835070461,1.35715830109503"
      },
      {
        "name": "Opp Marymount Stn",
        "code": "53129",
        "latlng": "103.839780332724,1.34968057726484"
      },
      {
        "name": "Opp Ai Tong Sch",
        "code": "53359",
        "latlng": "103.831961666974,1.3612566670212"
      },
      {
        "name": "Opp Raffles Inst",
        "code": "53309",
        "latlng": "103.845272500123,1.34849137843409"
      },
      {
        "name": "Opp Bright Hill Tp",
        "code": "53339",
        "latlng": "103.836783611091,1.36312998205054"
      },
      {
        "name": "Blk 131",
        "code": "53409",
        "latlng": "103.851268056215,1.34534609724648"
      },
      {
        "name": "Blk 245",
        "code": "53379",
        "latlng": "103.843860207135,1.36018670154819"
      },
      {
        "name": "Opp Kuo Chuan Presby Sch",
        "code": "53271",
        "latlng": "103.853918337934,1.34934788731465"
      },
      {
        "name": "Blk 202",
        "code": "53399",
        "latlng": "103.847016324944,1.35464002820881"
      },
      {
        "name": "Bishan Int",
        "code": "53009",
        "latlng": "103.849880837223,1.35045541249508"
      }
    ],
    [
      {
        "name": "Opp Bishan Stadium",
        "code": "53261",
        "latlng": "103.851790555395,1.35285975794277"
      },
      {
        "name": "Kuo Chuan Presby Sch",
        "code": "53279",
        "latlng": "103.853913028257,1.34970265350002"
      },
      {
        "name": "Bishan Nth Shop Mall",
        "code": "53381",
        "latlng": "103.844962120093,1.35830432828189"
      },
      {
        "name": "Opp Blk 131",
        "code": "53401",
        "latlng": "103.850488888977,1.34541666697777"
      },
      {
        "name": "CityCab",
        "code": "53321",
        "latlng": "103.840294721981,1.3613499999999"
      },
      {
        "name": "Raffles Inst",
        "code": "53301",
        "latlng": "103.84592361101,1.34861138900152"
      },
      {
        "name": "Blk 407",
        "code": "53341",
        "latlng": "103.833941666977,1.36355638900186"
      },
      {
        "name": "Marymount Stn",
        "code": "53121",
        "latlng": "103.839474185691,1.35016694219323"
      },
      {
        "name": "Blk 454",
        "code": "53361",
        "latlng": "103.830320833008,1.3592983329658"
      },
      {
        "name": "Sin Ming Plaza",
        "code": "53179",
        "latlng": "103.835823106951,1.35303963373308"
      },
      {
        "name": "Opp Thomson Plaza",
        "code": "53059",
        "latlng": "103.831480413616,1.35539998953207"
      },
      {
        "name": "Bef Thomson Plaza",
        "code": "53051",
        "latlng": "103.83247444401,1.35449694398821"
      },
      {
        "name": "Blk 314",
        "code": "53299",
        "latlng": "103.837945461281,1.35174011670393"
      },
      {
        "name": "Opp Blk 454",
        "code": "53369",
        "latlng": "103.830145597454,1.35947344252329"
      },
      {
        "name": "Sunrise Co Pte Ltd",
        "code": "53319",
        "latlng": "103.841248333023,1.34722500001454"
      },
      {
        "name": "Bishan Pk Sec Sch",
        "code": "53349",
        "latlng": "103.833703611003,1.36362111099296"
      },
      {
        "name": "Blk 117",
        "code": "53419",
        "latlng": "103.84980877523,1.34639996494851"
      },
      {
        "name": "Opp CityCab",
        "code": "53329",
        "latlng": "103.840495498598,1.36153970079137"
      },
      {
        "name": "Blk 169",
        "code": "53281",
        "latlng": "103.854320832969,1.34665638902112"
      },
      {
        "name": "Opp Bishan Nth Shop Mall",
        "code": "53389",
        "latlng": "103.845169338808,1.35804473736908"
      },
      {
        "name": "Bishan Int",
        "code": "53009",
        "latlng": "103.849880837223,1.35045541249508"
      },
      {
        "name": "Bishan Stadium",
        "code": "53269",
        "latlng": "103.851119016749,1.35335792415234"
      }
    ]
  ]
}
