{
  "number": "911",
  "direction": [
    [
      {
        "name": "Woodlands Reg Int",
        "code": "46009",
        "latlng": "103.784362086948,1.43618016136977"
      },
      {
        "name": "Blk 825",
        "code": "46281",
        "latlng": "103.790025895024,1.43878695707853"
      },
      {
        "name": "Evergreen Sec Sch",
        "code": "46421",
        "latlng": "103.793537796702,1.44087032562813"
      },
      {
        "name": "Evergreen Sec Sch",
        "code": "46411",
        "latlng": "103.794419161271,1.44270591766693"
      },
      {
        "name": "Blk 840",
        "code": "46431",
        "latlng": "103.7922556519,1.44397726846817"
      },
      {
        "name": "Blk 816",
        "code": "46441",
        "latlng": "103.789737109777,1.4421946582662"
      },
      {
        "name": "Blk 808",
        "code": "46261",
        "latlng": "103.78694461351,1.44256309213755"
      },
      {
        "name": "Blk 803",
        "code": "46279",
        "latlng": "103.78690125681,1.44021958652554"
      },
      {
        "name": "Riverside Sec Sch",
        "code": "46251",
        "latlng": "103.789086300318,1.44092236169211"
      },
      {
        "name": "Blk 875",
        "code": "46449",
        "latlng": "103.790037277034,1.44235503567334"
      },
      {
        "name": "Blk 880",
        "code": "46439",
        "latlng": "103.792650071909,1.44413536712588"
      },
      {
        "name": "Evergreen Pr Sch",
        "code": "46419",
        "latlng": "103.794098015187,1.44356110989542"
      },
      {
        "name": "Blk 856",
        "code": "46429",
        "latlng": "103.793150000034,1.44071444400749"
      },
      {
        "name": "Blk 891C CP",
        "code": "46289",
        "latlng": "103.790911983232,1.43872239825736"
      },
      {
        "name": "Woodlands Reg Int",
        "code": "46008",
        "latlng": "103.78517900264,1.43649291379325"
      },
      {
        "name": "Opp Blk 101",
        "code": "46559",
        "latlng": "103.781277226094,1.43550165536011"
      },
      {
        "name": "Blk 178",
        "code": "46569",
        "latlng": "103.777458809486,1.43472154667202"
      },
      {
        "name": "Blk 154",
        "code": "46579",
        "latlng": "103.775522499974,1.43488583298135"
      },
      {
        "name": "Blk 146",
        "code": "46589",
        "latlng": "103.774108634066,1.43632306005293"
      },
      {
        "name": "Woodlands Town Gdn",
        "code": "46509",
        "latlng": "103.770964322837,1.43804390195241"
      },
      {
        "name": "Woodlands Train Checkpt",
        "code": "46069",
        "latlng": "103.769338337993,1.44288948418443"
      },
      {
        "name": "Opp Blk 1A",
        "code": "46088",
        "latlng": "103.771086605944,1.44180914262914"
      },
      {
        "name": "Opp Woodlands Town Gdn",
        "code": "46501",
        "latlng": "103.771189129805,1.43796940271693"
      },
      {
        "name": "Opp Blk 146",
        "code": "46581",
        "latlng": "103.773796367064,1.43644118910045"
      },
      {
        "name": "Opp Blk 154",
        "code": "46571",
        "latlng": "103.775853535788,1.43475417848475"
      },
      {
        "name": "Opp Blk 178",
        "code": "46561",
        "latlng": "103.777190029125,1.43461192439866"
      },
      {
        "name": "Blk 101",
        "code": "46551",
        "latlng": "103.781623364648,1.43532728240853"
      },
      {
        "name": "Woodlands Reg Int",
        "code": "46009",
        "latlng": "103.784362086948,1.43618016136977"
      },
      {
        "name": "Blk 825",
        "code": "46281",
        "latlng": "103.790025895024,1.43878695707853"
      },
      {
        "name": "Evergreen Sec Sch",
        "code": "46421",
        "latlng": "103.793537796702,1.44087032562813"
      },
      {
        "name": "Evergreen Sec Sch",
        "code": "46411",
        "latlng": "103.794419161271,1.44270591766693"
      },
      {
        "name": "Blk 840",
        "code": "46431",
        "latlng": "103.7922556519,1.44397726846817"
      },
      {
        "name": "Blk 816",
        "code": "46441",
        "latlng": "103.789737109777,1.4421946582662"
      },
      {
        "name": "Blk 808",
        "code": "46261",
        "latlng": "103.78694461351,1.44256309213755"
      },
      {
        "name": "Blk 803",
        "code": "46279",
        "latlng": "103.78690125681,1.44021958652554"
      },
      {
        "name": "Riverside Sec Sch",
        "code": "46251",
        "latlng": "103.789086300318,1.44092236169211"
      },
      {
        "name": "Blk 875",
        "code": "46449",
        "latlng": "103.790037277034,1.44235503567334"
      },
      {
        "name": "Blk 880",
        "code": "46439",
        "latlng": "103.792650071909,1.44413536712588"
      },
      {
        "name": "Evergreen Pr Sch",
        "code": "46419",
        "latlng": "103.794098015187,1.44356110989542"
      },
      {
        "name": "Blk 856",
        "code": "46429",
        "latlng": "103.793150000034,1.44071444400749"
      },
      {
        "name": "Blk 891C CP",
        "code": "46289",
        "latlng": "103.790911983232,1.43872239825736"
      },
      {
        "name": "Woodlands Reg Int",
        "code": "46008",
        "latlng": "103.78517900264,1.43649291379325"
      }
    ]
  ]
}
