{
  "number": "NR6",
  "direction": [
    [
      {
        "name": "Resorts World Sentosa",
        "code": "14519",
        "latlng": "103.825703221274,1.25352193438109"
      },
      {
        "name": "VivoCity",
        "code": "14141",
        "latlng": "103.822109699271,1.26551350710168"
      },
      {
        "name": "HarbourFront Stn",
        "code": "14129",
        "latlng": "103.819778773911,1.2660786910177"
      },
      {
        "name": "Opp VivoCity",
        "code": "14119",
        "latlng": "103.82223995009,1.26596287004617"
      },
      {
        "name": "Keppel DP Blk 517",
        "code": "14109",
        "latlng": "103.827224905056,1.26804601553356"
      },
      {
        "name": "Opp Tg Pagar DP Blk F5",
        "code": "14089",
        "latlng": "103.829782065753,1.27044220444332"
      },
      {
        "name": "Marina Bay Sands MICE",
        "code": "03511",
        "latlng": "103.858972790274,1.28194708085559"
      },
      {
        "name": "Marina Bay Sands Theatre",
        "code": "03501",
        "latlng": "103.86061057793,1.28499944184777"
      },
      {
        "name": "Seating Gallery",
        "code": "02051",
        "latlng": "103.858917213117,1.28951669827309"
      },
      {
        "name": "The Esplanade",
        "code": "02061",
        "latlng": "103.856496607761,1.28987200772086"
      },
      {
        "name": "St. Andrew's Cath",
        "code": "04167",
        "latlng": "103.85161890405,1.2927352521308"
      },
      {
        "name": "Opp The Treasury",
        "code": "04249",
        "latlng": "103.850262165082,1.29043039362629"
      },
      {
        "name": "Boat Quay",
        "code": "05029",
        "latlng": "103.848333437503,1.2872465656158"
      },
      {
        "name": "Clarke Quay Stn",
        "code": "04222",
        "latlng": "103.847089049847,1.28898533877871"
      },
      {
        "name": "Clarke Quay",
        "code": "04211",
        "latlng": "103.847124443981,1.29043611099237"
      },
      {
        "name": "Liang Ct",
        "code": "04331",
        "latlng": "103.845040893827,1.29183939431483"
      },
      {
        "name": "UE Sq",
        "code": "13109",
        "latlng": "103.842724167027,1.29350944398373"
      },
      {
        "name": "Bef AA Ctr",
        "code": "13099",
        "latlng": "103.839618431514,1.29577667322401"
      },
      {
        "name": "The Morningside",
        "code": "13089",
        "latlng": "103.836041111034,1.29575111096692"
      },
      {
        "name": "Aft ERC Inst",
        "code": "13079",
        "latlng": "103.832558610993,1.29616972198432"
      },
      {
        "name": "Aft Zion Full Gospel Ch",
        "code": "13141",
        "latlng": "103.82996320725,1.29745598928708"
      },
      {
        "name": "Paterson Lodge",
        "code": "13191",
        "latlng": "103.829877992486,1.30266053145862"
      },
      {
        "name": "Tang Plaza",
        "code": "09047",
        "latlng": "103.832670558183,1.30465671962795"
      },
      {
        "name": "Lucky Plaza",
        "code": "09048",
        "latlng": "103.834084301101,1.30389539776251"
      },
      {
        "name": "Opp Meritus Mandarin",
        "code": "09037",
        "latlng": "103.837012533882,1.30234004202856"
      },
      {
        "name": "Midpoint Orchard",
        "code": "09038",
        "latlng": "103.838524818423,1.30154262450459"
      },
      {
        "name": "Orchard Plaza",
        "code": "08137",
        "latlng": "103.841005008168,1.30073968408287"
      },
      {
        "name": "Concorde Hotel S'pore",
        "code": "08138",
        "latlng": "103.841855810105,1.3004700069879"
      },
      {
        "name": "Dhoby Ghaut Stn",
        "code": "08057",
        "latlng": "103.845305442832,1.29933305354697"
      },
      {
        "name": "Macdonald Hse",
        "code": "08058",
        "latlng": "103.846541152712,1.29895834316201"
      },
      {
        "name": "NTUC Income Prinsep Hse",
        "code": "08079",
        "latlng": "103.84910329218,1.29921444445479"
      },
      {
        "name": "Peace Ctr",
        "code": "07011",
        "latlng": "103.849825653923,1.30099913210086"
      },
      {
        "name": "Selegie Ctr",
        "code": "07021",
        "latlng": "103.849957767669,1.30324521574422"
      },
      {
        "name": "Tekka Ctr",
        "code": "07031",
        "latlng": "103.851205833032,1.30572083298314"
      },
      {
        "name": "Broadway Hotel",
        "code": "07111",
        "latlng": "103.853175199407,1.30879366465825"
      },
      {
        "name": "Sri Srinivasa Perumal Tp",
        "code": "07211",
        "latlng": "103.856356143971,1.31313747728368"
      },
      {
        "name": "Sri Vadapathira K Tp",
        "code": "07221",
        "latlng": "103.857882704321,1.3150327865669"
      },
      {
        "name": "Kwong Wai Shiu Hosp",
        "code": "60101",
        "latlng": "103.860040424832,1.31783421341225"
      },
      {
        "name": "Boon Keng Stn",
        "code": "60121",
        "latlng": "103.861797811465,1.32008815616305"
      },
      {
        "name": "Opp Bendemeer Pr Sch",
        "code": "60141",
        "latlng": "103.863856827336,1.32258753767929"
      },
      {
        "name": "St. Michael's Pl",
        "code": "60161",
        "latlng": "103.865567308105,1.32477289725431"
      },
      {
        "name": "Leong Bee Ct",
        "code": "60201",
        "latlng": "103.868484016629,1.32932502261499"
      },
      {
        "name": "Potong Pasir Stn",
        "code": "60261",
        "latlng": "103.868917949306,1.33132471594281"
      },
      {
        "name": "Blk 103",
        "code": "61011",
        "latlng": "103.869464026158,1.333392798139"
      },
      {
        "name": "Aft Woodleigh Pk",
        "code": "61021",
        "latlng": "103.870188788764,1.33627668492922"
      },
      {
        "name": "Woodleigh Stn",
        "code": "61031",
        "latlng": "103.870449672628,1.33836472248715"
      },
      {
        "name": "Bef Braddell Rd",
        "code": "61041",
        "latlng": "103.870491943974,1.34142999996786"
      },
      {
        "name": "Aft Sommerville Rd",
        "code": "62111",
        "latlng": "103.870771712541,1.34509852230046"
      },
      {
        "name": "Aft Wolskel Rd",
        "code": "62121",
        "latlng": "103.871568098818,1.34682778451152"
      },
      {
        "name": "S'goon Stn",
        "code": "62131",
        "latlng": "103.872774327976,1.34897900642242"
      },
      {
        "name": "Blk 261",
        "code": "66371",
        "latlng": "103.872685432406,1.35376730160469"
      },
      {
        "name": "Opp S'goon Swim Cplx",
        "code": "63361",
        "latlng": "103.873839853652,1.35744648841269"
      },
      {
        "name": "Bef St. Helier's Ave",
        "code": "63181",
        "latlng": "103.873462222016,1.36083138898258"
      },
      {
        "name": "Aft S'goon Nth Ave 1",
        "code": "63191",
        "latlng": "103.874039721994,1.36426277802706"
      },
      {
        "name": "Blk 133",
        "code": "63201",
        "latlng": "103.874928623034,1.36616837676559"
      },
      {
        "name": "Blk 138",
        "code": "63211",
        "latlng": "103.875730840116,1.36814638231184"
      },
      {
        "name": "Opp Gracehaven S Army",
        "code": "64101",
        "latlng": "103.876547716555,1.37211286888309"
      },
      {
        "name": "Ctrl Pl",
        "code": "64491",
        "latlng": "103.879051667003,1.37513027801162"
      },
      {
        "name": "Bet Blks 930/931",
        "code": "64481",
        "latlng": "103.88078641408,1.37514474329334"
      },
      {
        "name": "Blk 917",
        "code": "64471",
        "latlng": "103.883967777989,1.37454805598776"
      },
      {
        "name": "Opp Montfort Sch",
        "code": "64351",
        "latlng": "103.888082121754,1.37481110511314"
      },
      {
        "name": "Blk 535",
        "code": "64361",
        "latlng": "103.890548944458,1.37634509209584"
      },
      {
        "name": "Blk 436",
        "code": "64031",
        "latlng": "103.893660799245,1.37699995735935"
      },
      {
        "name": "Blk 458",
        "code": "64021",
        "latlng": "103.896632505092,1.37787641446624"
      },
      {
        "name": "Opp The Rivervale",
        "code": "65011",
        "latlng": "103.897213087053,1.38158507096956"
      },
      {
        "name": "Blk 101",
        "code": "67169",
        "latlng": "103.899222223375,1.38253470078481"
      },
      {
        "name": "Blk 112",
        "code": "67159",
        "latlng": "103.902256191627,1.38437170390198"
      },
      {
        "name": "Opp Blk 121",
        "code": "67139",
        "latlng": "103.904175771858,1.38715714684692"
      },
      {
        "name": "Blk 137",
        "code": "67129",
        "latlng": "103.904988920052,1.38936844113717"
      },
      {
        "name": "Blk 128",
        "code": "67119",
        "latlng": "103.903235820656,1.39050824372015"
      },
      {
        "name": "Blk 235",
        "code": "67109",
        "latlng": "103.899986698136,1.39102885574125"
      },
      {
        "name": "Sengkang Stn",
        "code": "67409",
        "latlng": "103.896068166064,1.39233915683053"
      },
      {
        "name": "Blk 325 CP",
        "code": "67399",
        "latlng": "103.891670105856,1.39385005995802"
      },
      {
        "name": "Blk 319A",
        "code": "N6709",
        "latlng": "103.889747264968,1.39104204877012"
      },
      {
        "name": "Blk 321 CP",
        "code": "67351",
        "latlng": "103.891354545402,1.38994475443136"
      },
      {
        "name": "Opp Blk 204 CP",
        "code": "67341",
        "latlng": "103.895051690314,1.38864779457095"
      },
      {
        "name": "Blk 225A",
        "code": "67171",
        "latlng": "103.898979777157,1.3873125717061"
      },
      {
        "name": "Blk 117A",
        "code": "67151",
        "latlng": "103.902157881268,1.38352301806621"
      },
      {
        "name": "Opp Blk 101",
        "code": "67161",
        "latlng": "103.899268333012,1.38212499997751"
      },
      {
        "name": "The Rivervale",
        "code": "65019",
        "latlng": "103.897493330993,1.38151169885023"
      },
      {
        "name": "Opp Blk 458",
        "code": "64029",
        "latlng": "103.896888548849,1.37781998070081"
      },
      {
        "name": "Blk 434",
        "code": "64039",
        "latlng": "103.893937612181,1.37668753222313"
      },
      {
        "name": "Blk 532",
        "code": "64369",
        "latlng": "103.891493538677,1.37634448413796"
      },
      {
        "name": "Montfort Sch",
        "code": "64359",
        "latlng": "103.889187607764,1.37528677811118"
      },
      {
        "name": "Blk 665",
        "code": "64479",
        "latlng": "103.883539951216,1.37440134071298"
      },
      {
        "name": "Blk 946A",
        "code": "64489",
        "latlng": "103.880676883971,1.3748876498172"
      },
      {
        "name": "Opp Ctrl Pl",
        "code": "64499",
        "latlng": "103.87828864497,1.37488285660708"
      },
      {
        "name": "Gracehaven S Army",
        "code": "64109",
        "latlng": "103.876909004498,1.37202330151758"
      },
      {
        "name": "Opp Blk 139",
        "code": "63219",
        "latlng": "103.876271048335,1.36856637012728"
      },
      {
        "name": "Toho Green",
        "code": "63209",
        "latlng": "103.875226938569,1.36606471066101"
      },
      {
        "name": "Aft S'goon Nth Ave 1",
        "code": "63199",
        "latlng": "103.873838055988,1.36327972197529"
      },
      {
        "name": "Aft S'goon Gdn Way",
        "code": "63189",
        "latlng": "103.873634609604,1.36133997852945"
      },
      {
        "name": "Bef Tai Seng Chr Ch",
        "code": "63179",
        "latlng": "103.873935327762,1.35999305129182"
      },
      {
        "name": "S'goon Sports Cplx",
        "code": "63369",
        "latlng": "103.874103888988,1.35663166702766"
      },
      {
        "name": "Blk 206",
        "code": "66379",
        "latlng": "103.8728580165,1.3533915586216"
      },
      {
        "name": "S'goon Stn",
        "code": "62139",
        "latlng": "103.873411659358,1.34904612405752"
      },
      {
        "name": "Blk 403",
        "code": "62129",
        "latlng": "103.872054885247,1.34698958928377"
      },
      {
        "name": "Aft Sunshine Lodge",
        "code": "62119",
        "latlng": "103.871092200305,1.34483265931432"
      },
      {
        "name": "Aft Bartley Rd",
        "code": "61049",
        "latlng": "103.870968611033,1.34196277802455"
      },
      {
        "name": "Woodleigh Stn",
        "code": "61039",
        "latlng": "103.870848817836,1.33845332842076"
      },
      {
        "name": "Opp Woodleigh Pk",
        "code": "61029",
        "latlng": "103.870515883427,1.33596832935316"
      },
      {
        "name": "Opp Blk 101",
        "code": "61019",
        "latlng": "103.869761667034,1.33320166700794"
      },
      {
        "name": "Potong Pasir Stn",
        "code": "60269",
        "latlng": "103.869228909506,1.33099030126829"
      },
      {
        "name": "Opp Leong Bee Ct",
        "code": "60209",
        "latlng": "103.868960995656,1.32986133945908"
      },
      {
        "name": "Aft Jln Kolam Ayer",
        "code": "60179",
        "latlng": "103.868340251238,1.32634025655349"
      },
      {
        "name": "Blk 54",
        "code": "60159",
        "latlng": "103.867641960029,1.32409476572402"
      },
      {
        "name": "Blk 44",
        "code": "60139",
        "latlng": "103.86628982238,1.32204861560059"
      },
      {
        "name": "Opp Blk 28",
        "code": "60119",
        "latlng": "103.864214862088,1.31889711409004"
      },
      {
        "name": "Bef Lavender St",
        "code": "60099",
        "latlng": "103.861355781584,1.31518614599909"
      },
      {
        "name": "Hoa Nam Bldg",
        "code": "07329",
        "latlng": "103.859890882885,1.31284472583349"
      },
      {
        "name": "Aft Allenby Rd",
        "code": "07319",
        "latlng": "103.85870666697,1.3103883329971"
      },
      {
        "name": "Opp Veerasamy Rd",
        "code": "07419",
        "latlng": "103.856163024931,1.30653024120782"
      },
      {
        "name": "Bef Sim Lim Twr",
        "code": "07529",
        "latlng": "103.854512280133,1.3039649255683"
      },
      {
        "name": "Opp Burlington Sq",
        "code": "07517",
        "latlng": "103.852525646511,1.30138184852014"
      },
      {
        "name": "Opp Prime Ctr",
        "code": "07571",
        "latlng": "103.851140093146,1.30063444632182"
      },
      {
        "name": "Non Stop",
        "code": "E0700",
        "latlng": "0.0,0.0"
      },
      {
        "name": "Non Stop",
        "code": "E0807",
        "latlng": "0.0,0.0"
      },
      {
        "name": "Non Stop",
        "code": "E0402",
        "latlng": "0.0,0.0"
      },
      {
        "name": "SMU",
        "code": "07509",
        "latlng": "103.849040999998,1.29734200002622"
      },
      {
        "name": "YMCA",
        "code": "08041",
        "latlng": "103.847832543133,1.2980744505163"
      },
      {
        "name": "Dhoby Ghaut Stn",
        "code": "08031",
        "latlng": "103.845256959553,1.29831153783483"
      },
      {
        "name": "Winsland Hse",
        "code": "08111",
        "latlng": "103.840943409506,1.29984311306454"
      },
      {
        "name": "Somerset Stn",
        "code": "08121",
        "latlng": "103.838776184597,1.3002756932648"
      },
      {
        "name": "Opp Ngee Ann City",
        "code": "09011",
        "latlng": "103.834316723768,1.30211335092268"
      },
      {
        "name": "Opp Orchard Stn",
        "code": "09022",
        "latlng": "103.83239784276,1.3025283477354"
      },
      {
        "name": "Opp Paterson Lodge",
        "code": "13199",
        "latlng": "103.829992325055,1.30229926867405"
      },
      {
        "name": "Bef Zion Full Gospel Ch",
        "code": "13159",
        "latlng": "103.830531835552,1.29796011528413"
      },
      {
        "name": "Opp ERC Inst",
        "code": "13071",
        "latlng": "103.833214044556,1.29634047619829"
      },
      {
        "name": "Airview Twr",
        "code": "13081",
        "latlng": "103.836242777988,1.29591138900948"
      },
      {
        "name": "Aft AA Ctr",
        "code": "13091",
        "latlng": "103.839378056019,1.29593138900378"
      },
      {
        "name": "Opp Mohd Sultan Rd",
        "code": "13101",
        "latlng": "103.842312097577,1.29414162678696"
      },
      {
        "name": "Opp Liang Ct",
        "code": "04339",
        "latlng": "103.844641488302,1.29257766944113"
      },
      {
        "name": "Opp Clarke Quay",
        "code": "04219",
        "latlng": "103.84686777837,1.29096802754676"
      },
      {
        "name": "Boat Quay",
        "code": "05029",
        "latlng": "103.848333437503,1.2872465656158"
      },
      {
        "name": "OCBC Ctr",
        "code": "05319",
        "latlng": "103.849086858503,1.2844966730172"
      },
      {
        "name": "One Raffles Quay",
        "code": "03059",
        "latlng": "103.851356525795,1.28097649555869"
      },
      {
        "name": "UIC Bldg",
        "code": "03129",
        "latlng": "103.849567181238,1.27807003531954"
      },
      {
        "name": "Opp MAS Bldg",
        "code": "03218",
        "latlng": "103.846878096253,1.27411665186177"
      },
      {
        "name": "Opp Customs Port Br HQ",
        "code": "05649",
        "latlng": "103.840939122181,1.27238421221025"
      },
      {
        "name": "Opp Former Railway Stn",
        "code": "14061",
        "latlng": "103.838616788163,1.27230912869304"
      },
      {
        "name": "Keppel Workshop",
        "code": "14071",
        "latlng": "103.833841910023,1.27224625438855"
      },
      {
        "name": "Tg Pagar DP Blk F5",
        "code": "14081",
        "latlng": "103.830613678712,1.27067760623648"
      },
      {
        "name": "Opp Keppel DP Blk 517",
        "code": "14101",
        "latlng": "103.82825805601,1.26837500002352"
      },
      {
        "name": "Resorts World Sentosa",
        "code": "14519",
        "latlng": "103.825703221274,1.25352193438109"
      }
    ]
  ]
}
